proj1/AnimatedColor/NZRbitGEN.v
// NZRbitGEN.v
// Generate NZR line code timing for WS2812B GRB LED Module,
// using a Digilent BASYS3 prototyping board with a
// Xilinx Artix-7 FPGA clocked at 100 MHz.
//
// This module must receive input qmode which specifies
// the current NZR  line code to be produced (for a "0", "1", RESET).
// The value of qmode should be held constant until
// the Moore output bdone is asserted.  A new qmode should
// then be supplied within 1/100M = 10 ns to begin the generation
// of the next line code.
//
// Adapted from earlier code by Jerry C. Hamann
// Modified for new production WB2812B with RESET > 280 us
//  qmode must supply at least 219 bit times of 1.28 us 
//   of state 10 to meet the new reset time of > 280 us
// EE 4490 
//
module NZRbitGEN(bout, bdone, qmode, startcoding, clk, reset);
  output  bout, bdone;  // bout  -- NZR signal
                          // bdone -- line code generation completed
  input   [1:0] qmode;  // Mode for generation:
                          // 2'b00 Produce a "0"
                          // 2'b01 Produce a "1"
                          // 2'b10 Solid low output (for resets)
                          // 2'b11 Solid high output (not used in WB2812B)
  input   startcoding;  // Like reset, drives counter to zero to synchronize code generation
  input   clk, reset;   // synchronous, 100 MHz assumed
  reg     bout;          
  reg     [6:0] bcount; // 0-127 count for generating NZR timing of a bit
                          // Note:  128*(1/100MHz) = 1.28 us (close enough to 1.25 us)

  // Implement state memory and next state for synchronous bcounter for bit time
  always @(posedge clk)
  // Depends on 7'h7F->7'h00 rollover at 1.28 us
  begin
    if(reset || startcoding)
      bcount <= 0;
    else
      bcount <= bcount+1; 
   end

  always @(qmode or bcount) // bout produced based on qmode
  begin
    // 36*(1/(100 MHz)) = 0.36 us = 28% of 1.28 us
    // 92*(1/(100 MHz)) = 0.92 us = 72% of 1.28 us
    case(qmode)         
      2'b00:  bout = (bcount < 36) ? 1 : 0 ; // "0" in 1.28 us
      2'b01:  bout = (bcount < 92) ? 1 : 0 ; // "1" in 1.28 us
      2'b10:  bout = 0; // Produces "RESET" output, stays low
      2'b11:  bout = 1; // Reserved for future use
      default: bout = 0;
    endcase
  end

  assign bdone = (bcount == 127);  // Marks end of bit period
endmodule

proj1/AnimatedColor2/BitCounter.v
// BitCounter.v
// Just a simple 8-bit synchronous counter
// Main inputs and outputs connect to GRBStateMachine
// Value of output Count keeps track of how many bits have been sent
// This implies a max of 10 LED modules could be used (240 bits)
// For longer LED strips, increase the bit width of the counter

module BitCounter(Count,ClearCounter,IncCounter,clk,reset);
  output  [7:0] Count;
  input   ClearCounter, IncCounter;
  input   clk, reset;

  reg [7:0] Count, nCount;

  always @(posedge clk)
    if(reset) Count <= 0;
    else Count <= nCount;

  always @(reset, Count, ClearCounter, IncCounter)
    if(reset || ClearCounter)
      nCount = 0;
    else if(IncCounter)
      nCount = Count+1;
    else
      nCount = Count;
endmodule

ShiftRegister.v
// ShiftRegister.v
// determines the 24-bit control word for an LED module
// shifts it out one bit at a time
// keeps sending the same 24 bits, so same color to all modules

module ShiftRegister(CurrentBit,sw,LoadRegister,RotateRegisterLeft,clk,reset);
  output CurrentBit;
  input  [15:4] sw;
  input  LoadRegister, RotateRegisterLeft;
  input  clk, reset;

  parameter DEFAULTREG=24'h0F0F0F;  // white, half brightness

  reg [23:0]  TheReg, nTheReg;  // 24 bits for GRB control

  always @(posedge clk)
    if(reset) TheReg <= DEFAULTREG;
    else  TheReg <= nTheReg;
      
    // switches set the upper 4 bits of the GRB control bytes
  always @(TheReg, LoadRegister, RotateRegisterLeft, sw)
    if(LoadRegister)
      nTheReg = {sw[15:12],4'b0000,sw[11:8],4'b0000,sw[7:4],4'b0000};
    else if(RotateRegisterLeft)
      nTheReg = {TheReg[22:0],TheReg[23]};
    else
      nTheReg = TheReg;

  assign  CurrentBit = TheReg[23];
endmodule

proj1/AnimatedColor/GRBStateMachine.v
// GRBStateMachine.v
// Output qmode tells the NZRbitGEN module whether to send a 0, 1, RESET
// Updated to support new WS2812B reset code of > 280 us
// bdone ticks every bit period (1.28 us), RESET is > 280 us, use 281000 clks = 281 us

module GRBStateMachine(qmode,Done,LoadGRBPattern,ShiftPattern,StartCoding,
          ClrCounter,IncCounter,ShipGRB,theBit,bdone,Count,NumLEDs,clk,reset,allDone);
	output	[1:0]	qmode;
	output	allDone, Done, LoadGRBPattern, ShiftPattern, StartCoding, ClrCounter, IncCounter;
	input		ShipGRB, theBit, bdone;
	input   [7:0]	Count;
	input   [3:1] NumLEDs;
	input		clk, reset;
  
  reg	     	S, nS;
	parameter	SSHIPRET=1'b0, SSHIPGRB=1'b1;

  reg      [7:0]   COMPAREVAL;
  reg      [14:0]  rCount;  // counter for RESET time

	always @(posedge clk)
		if(reset)
			S <= SSHIPRET;
		else
			S <= nS;

	always @(S, ShipGRB, bdone, Count)
		case(S)
			SSHIPRET:  nS = ShipGRB ? SSHIPGRB : SSHIPRET;
			SSHIPGRB:  nS = (bdone && (Count==COMPAREVAL)) ? SSHIPRET : SSHIPGRB;
			default:   nS = SSHIPRET;
		endcase

	assign LoadGRBPattern = (S==SSHIPRET)&&ShipGRB;
	assign ClrCounter     = (S==SSHIPRET)&&ShipGRB;
	assign StartCoding    = (S==SSHIPRET)&&ShipGRB;
	assign ShiftPattern   = (S==SSHIPGRB)&&bdone;
	assign IncCounter     = (S==SSHIPGRB)&&bdone;
	assign qmode          = (S==SSHIPRET) ? 2'b10 : {1'b0,theBit};
	assign Done           = (S==SSHIPGRB)&&bdone&&(Count==COMPAREVAL);
	assign allDone        = (S==SSHIPRET)&&(rCount==15'd28100); // 281 us

//	assign allDone  = (S==SSHIPRET)&&(rCount==15'd3000); // for testing only  

  always @(NumLEDs)
    case(NumLEDs)  // how many LED modules?
      3'b001:  COMPAREVAL = 23;  // 1*24 = 24 bits
      3'b010:  COMPAREVAL = 47;  // 2*24 = 48 bits
      3'b011:  COMPAREVAL = 71;  // 3*24 = 72 bits
			3'b100:  COMPAREVAL = 95;  // 4*24 = 96 bits
      3'b101:  COMPAREVAL = 119; // 5*24 = 120 bits
      default: COMPAREVAL = 23;  // default to one module
    endcase

  always @(posedge clk)
  // counts time for RESET, 10 ns per tick
  begin
    if(reset || Done)  // Done sending bits, start RESET
      rCount <= 0;
    else if (S==SSHIPRET)
      rCount <= rCount+1; 
    else rCount <= rCount;
  end
 
endmodule

SSStateMachine.v
// SSStateMachine.v
// Allows user to reset system with SW0 or say "Go" with center button
//   as defined in xdc file
// Input Done comes from GRBStateMachine when it's sent all the bits
//   but not RESET yet 
// Input allDone comes from GRBStateMachine when it's sent the RESET code
// Incorporates debouncing delay for the button
// Output shipGRB tells GRBStateMachine to keep sending data bits 
// Updated to support new WS2812B reset code of > 280 us

module SSStateMachine(shipGRB,Done,Go,clk,reset,allDone,Ready2Go);
	output	shipGRB, Ready2Go;
	input	allDone, Done, Go;
	input	clk, reset;

	reg [1:0]	S, nS;
	parameter	SWAIT=2'b00, SSHIP=2'b01, SRET=2'b10, SDBOUNCE=2'b11;

	always @(posedge clk)
		if(reset)
			S <= SWAIT;
		else
			S <= nS;

	always @(S, Go, Done, allDone)
		case(S)
			SWAIT: 		nS = Go      ? SSHIP    : SWAIT;
			SSHIP:		nS = Done    ? SRET     : SSHIP;
      SRET:		  nS = allDone ? SDBOUNCE : SRET;
			SDBOUNCE:	nS = Go      ? SDBOUNCE : SWAIT;
			default:	nS = SWAIT;
		endcase

  assign Ready2Go = (S==SWAIT);  // okay to press Go
	assign shipGRB  = (S==SSHIP);  // send data bits
endmodule

proj1/AnimatedColor/ClockDivide.v
// EE 4490: Homework Set 04
// Problem 1: ClockDivide module
// Bruce Coburn

module ClockDivide(secTick, clk);
	output     	 	secTick;
	input			clk;
	reg 	[26:0] 	ClockTick;
	reg             nextTick;
	
parameter DIVISOR = 27'd100000000;	// Will take our 100MHz on-board clock
										// and will divide it to make a 1Hz 
										// "new clock"
	
	always@(posedge clk)
	begin
	   ClockTick <= ClockTick + 27'd1;
	   
	   if(ClockTick > DIVISOR/2) nextTick <= 1'b0;
	   else if(ClockTick <= DIVISOR/2) nextTick <=1'b1;
	   
	   if(ClockTick >= (DIVISOR-1))
	       ClockTick <= 27'd0;
    end
	
	assign secTick = nextTick;
		
endmodule

proj1/AnimatedColor/SimpleSend.v
// SimpleSend.v
// top-level module for WS2812B LED strip
// VERY basic design, sends same color to all modules
// Updated to support new WS2812B reset code of > 280 us

//module SimpleSend(dataOut,sw,NumLEDs,Go,clk,reset,Ready2Go);
module SimpleSend(dataOut,sw,NumLEDs,clk,reset,Ready2Go);
	output	dataOut, Ready2Go;
	input   [15:4] sw;
	input   [3:1]  NumLEDs;
//	input	Go, clk, reset;
    input	clk, reset;
	
	wire		shipGRB, Done, allDone, Go;
	wire [1:0]	qmode;
	wire		LoadGRBPattern, ShiftPattern, StartCoding, ClrCounter, IncCounter, theBit, bdone;
	wire [7:0]	Count;

    ClockDivide     cdiv(Go, clk);
	SSStateMachine	sssm(shipGRB,Done,Go,clk,reset,allDone,Ready2Go);
	GRBStateMachine grbsm(qmode,Done,LoadGRBPattern,ShiftPattern,StartCoding,ClrCounter,IncCounter,
                              shipGRB,theBit,bdone,Count,NumLEDs,clk,reset,allDone);
	ShiftRegister   shftr(theBit,sw,LoadGRBPattern,ShiftPattern,clk,reset);
	BitCounter	btcnt(Count,ClrCounter,IncCounter,clk,reset);
	NZRbitGEN	nzrgn(dataOut,bdone,qmode,StartCoding,clk,reset);
endmodule

proj1/SimpleSend/tb_SimpleSend_top.v
// tb_SimpleSend_top.v
// test bench for WS2812B LED strip driver
// VERY basic design, sends same color to all modules

`timescale 1ns/1ns
module tb_SimpleSend_top;
	wire	dataOut, Ready2Go;
	reg   [15:4] sw;
	reg   [3:1]  NumLEDs;
	reg 	Go, clk, reset;

	SimpleSend  ssend(dataOut,sw,NumLEDs,Go,clk,reset,Ready2Go);
  
  always // Note:  1/100M = 10E-9
    #5 clk = !clk;

  initial begin
    $dumpfile("tb_SimpleSend_top.vcd");
    $dumpvars(0,tb_SimpleSend_top);
    clk=0; reset=1; Go=0; 
    //NumLEDs=3'b001;  // number of LED modules
    NumLEDs=3'b010;  // number of LED modules
    sw=12'h4A9;  // arbitrary setting for bits set to all modules
    #20 reset=0; 
  // reset is 281,000 ns
  // bits are 1,280 ns each, or 30,720 ns per module for 24 bits
  // that's 311,720 ns for just one module
  //#315000 $finish;  // for one module
  #720000 $finish;    // for two modules, two sw settings
   end  
  
  initial begin
    #40  Go=1;   // press Go button
    #80  Go=0;   // release Go button
    while(!Ready2Go) begin #10; end // Wait for Ready2Go indication
    #2000 sw=12'h864;  // arbitrary new setting for bits set to all modules
    #40  Go=1;   // press Go button
    #80  Go=0;   // release Go button     
  end  
endmodule

proj1/SimpleSend/tb_SimpleSend_top.vcd
$date
	Wed Aug 29 14:25:23 2018
$end
$version
	Icarus Verilog
$end
$timescale
	1ns
$end
$scope module tb_SimpleSend_top $end
$var wire 1 ! Ready2Go $end
$var wire 1 " dataOut $end
$var reg 1 # Go $end
$var reg 3 $ NumLEDs [3:1] $end
$var reg 1 % clk $end
$var reg 1 & reset $end
$var reg 12 ' sw [15:4] $end
$scope module ssend $end
$var wire 1 ( ClrCounter $end
$var wire 8 ) Count [7:0] $end
$var wire 1 * Done $end
$var wire 1 + Go $end
$var wire 1 , IncCounter $end
$var wire 1 - LoadGRBPattern $end
$var wire 3 . NumLEDs [3:1] $end
$var wire 1 ! Ready2Go $end
$var wire 1 / ShiftPattern $end
$var wire 1 0 StartCoding $end
$var wire 1 1 allDone $end
$var wire 1 2 bdone $end
$var wire 1 3 clk $end
$var wire 1 " dataOut $end
$var wire 2 4 qmode [1:0] $end
$var wire 1 5 reset $end
$var wire 1 6 shipGRB $end
$var wire 12 7 sw [15:4] $end
$var wire 1 8 theBit $end
$scope module sssm $end
$var wire 1 * Done $end
$var wire 1 + Go $end
$var wire 1 ! Ready2Go $end
$var wire 1 1 allDone $end
$var wire 1 3 clk $end
$var wire 1 5 reset $end
$var wire 1 6 shipGRB $end
$var reg 2 9 S [1:0] $end
$var reg 2 : nS [1:0] $end
$upscope $end
$scope module grbsm $end
$var wire 1 ( ClrCounter $end
$var wire 8 ; Count [7:0] $end
$var wire 1 * Done $end
$var wire 1 , IncCounter $end
$var wire 1 - LoadGRBPattern $end
$var wire 3 < NumLEDs [3:1] $end
$var wire 1 / ShiftPattern $end
$var wire 1 6 ShipGRB $end
$var wire 1 0 StartCoding $end
$var wire 1 1 allDone $end
$var wire 1 2 bdone $end
$var wire 1 3 clk $end
$var wire 2 = qmode [1:0] $end
$var wire 1 5 reset $end
$var wire 1 8 theBit $end
$var reg 8 > COMPAREVAL [7:0] $end
$var reg 1 ? S $end
$var reg 1 @ nS $end
$var reg 15 A rCount [14:0] $end
$upscope $end
$scope module shftr $end
$var wire 1 8 CurrentBit $end
$var wire 1 - LoadRegister $end
$var wire 1 / RotateRegisterLeft $end
$var wire 1 3 clk $end
$var wire 1 5 reset $end
$var wire 12 B sw [15:4] $end
$var reg 24 C TheReg [23:0] $end
$var reg 24 D nTheReg [23:0] $end
$upscope $end
$scope module btcnt $end
$var wire 1 ( ClearCounter $end
$var wire 1 , IncCounter $end
$var wire 1 3 clk $end
$var wire 1 5 reset $end
$var reg 8 E Count [7:0] $end
$var reg 8 F nCount [7:0] $end
$upscope $end
$scope module nzrgn $end
$var wire 1 2 bdone $end
$var wire 1 3 clk $end
$var wire 2 G qmode [1:0] $end
$var wire 1 5 reset $end
$var wire 1 0 startcoding $end
$var reg 7 H bcount [6:0] $end
$var reg 1 I bout $end
$upscope $end
$upscope $end
$upscope $end
$enddefinitions $end
#0
$dumpvars
0I
bx H
bx G
bx F
bx E
bx D
bx C
b10010101001 B
bx A
x@
x?
b101111 >
bx =
b10 <
bx ;
b0 :
bx 9
x8
b10010101001 7
x6
15
bx 4
03
x2
x1
x0
x/
b10 .
x-
x,
0+
x*
bx )
x(
b10010101001 '
1&
0%
b10 $
0#
0"
x!
$end
#5
0-
0(
00
b10 4
b10 =
b10 G
01
b11110000111100001111 D
08
b0 F
0*
0,
0/
0@
b0 9
1!
06
0?
b0 A
b11110000111100001111 C
b0 E
b0 )
b0 ;
b0 H
02
1%
13
#10
0%
03
#15
1%
13
#20
0%
03
0&
05
#25
b1 A
b1 H
1%
13
#30
0%
03
#35
b10 H
b10 A
1%
13
#40
b1 :
0%
03
1#
1+
#45
b10000001010000010010000 D
1-
1(
10
1@
b1 9
0!
16
b11 A
b11 H
1%
13
#50
0%
03
#55
1I
1"
0-
0(
00
b0 4
b0 =
b0 G
b0 H
b10000001010000010010000 C
b100 A
1?
1%
13
#60
0%
03
#65
b1 H
1%
13
#70
0%
03
#75
b10 H
1%
13
#80
0%
03
#85
b11 H
1%
13
#90
0%
03
#95
b100 H
1%
13
#100
0%
03
#105
b101 H
1%
13
#110
0%
03
#115
b110 H
1%
13
#120
0%
03
0#
0+
#125
b111 H
1%
13
#130
0%
03
#135
b1000 H
1%
13
#140
0%
03
#145
b1001 H
1%
13
#150
0%
03
#155
b1010 H
1%
13
#160
0%
03
#165
b1011 H
1%
13
#170
0%
03
#175
b1100 H
1%
13
#180
0%
03
#185
b1101 H
1%
13
#190
0%
03
#195
b1110 H
1%
13
#200
0%
03
#205
b1111 H
1%
13
#210
0%
03
#215
b10000 H
1%
13
#220
0%
03
#225
b10001 H
1%
13
#230
0%
03
#235
b10010 H
1%
13
#240
0%
03
#245
b10011 H
1%
13
#250
0%
03
#255
b10100 H
1%
13
#260
0%
03
#265
b10101 H
1%
13
#270
0%
03
#275
b10110 H
1%
13
#280
0%
03
#285
b10111 H
1%
13
#290
0%
03
#295
b11000 H
1%
13
#300
0%
03
#305
b11001 H
1%
13
#310
0%
03
#315
b11010 H
1%
13
#320
0%
03
#325
b11011 H
1%
13
#330
0%
03
#335
b11100 H
1%
13
#340
0%
03
#345
b11101 H
1%
13
#350
0%
03
#355
b11110 H
1%
13
#360
0%
03
#365
b11111 H
1%
13
#370
0%
03
#375
b100000 H
1%
13
#380
0%
03
#385
b100001 H
1%
13
#390
0%
03
#395
b100010 H
1%
13
#400
0%
03
#405
b100011 H
1%
13
#410
0%
03
#415
0I
0"
b100100 H
1%
13
#420
0%
03
#425
b100101 H
1%
13
#430
0%
03
#435
b100110 H
1%
13
#440
0%
03
#445
b100111 H
1%
13
#450
0%
03
#455
b101000 H
1%
13
#460
0%
03
#465
b101001 H
1%
13
#470
0%
03
#475
b101010 H
1%
13
#480
0%
03
#485
b101011 H
1%
13
#490
0%
03
#495
b101100 H
1%
13
#500
0%
03
#505
b101101 H
1%
13
#510
0%
03
#515
b101110 H
1%
13
#520
0%
03
#525
b101111 H
1%
13
#530
0%
03
#535
b110000 H
1%
13
#540
0%
03
#545
b110001 H
1%
13
#550
0%
03
#555
b110010 H
1%
13
#560
0%
03
#565
b110011 H
1%
13
#570
0%
03
#575
b110100 H
1%
13
#580
0%
03
#585
b110101 H
1%
13
#590
0%
03
#595
b110110 H
1%
13
#600
0%
03
#605
b110111 H
1%
13
#610
0%
03
#615
b111000 H
1%
13
#620
0%
03
#625
b111001 H
1%
13
#630
0%
03
#635
b111010 H
1%
13
#640
0%
03
#645
b111011 H
1%
13
#650
0%
03
#655
b111100 H
1%
13
#660
0%
03
#665
b111101 H
1%
13
#670
0%
03
#675
b111110 H
1%
13
#680
0%
03
#685
b111111 H
1%
13
#690
0%
03
#695
b1000000 H
1%
13
#700
0%
03
#705
b1000001 H
1%
13
#710
0%
03
#715
b1000010 H
1%
13
#720
0%
03
#725
b1000011 H
1%
13
#730
0%
03
#735
b1000100 H
1%
13
#740
0%
03
#745
b1000101 H
1%
13
#750
0%
03
#755
b1000110 H
1%
13
#760
0%
03
#765
b1000111 H
1%
13
#770
0%
03
#775
b1001000 H
1%
13
#780
0%
03
#785
b1001001 H
1%
13
#790
0%
03
#795
b1001010 H
1%
13
#800
0%
03
#805
b1001011 H
1%
13
#810
0%
03
#815
b1001100 H
1%
13
#820
0%
03
#825
b1001101 H
1%
13
#830
0%
03
#835
b1001110 H
1%
13
#840
0%
03
#845
b1001111 H
1%
13
#850
0%
03
#855
b1010000 H
1%
13
#860
0%
03
#865
b1010001 H
1%
13
#870
0%
03
#875
b1010010 H
1%
13
#880
0%
03
#885
b1010011 H
1%
13
#890
0%
03
#895
b1010100 H
1%
13
#900
0%
03
#905
b1010101 H
1%
13
#910
0%
03
#915
b1010110 H
1%
13
#920
0%
03
#925
b1010111 H
1%
13
#930
0%
03
#935
b1011000 H
1%
13
#940
0%
03
#945
b1011001 H
1%
13
#950
0%
03
#955
b1011010 H
1%
13
#960
0%
03
#965
b1011011 H
1%
13
#970
0%
03
#975
b1011100 H
1%
13
#980
0%
03
#985
b1011101 H
1%
13
#990
0%
03
#995
b1011110 H
1%
13
#1000
0%
03
#1005
b1011111 H
1%
13
#1010
0%
03
#1015
b1100000 H
1%
13
#1020
0%
03
#1025
b1100001 H
1%
13
#1030
0%
03
#1035
b1100010 H
1%
13
#1040
0%
03
#1045
b1100011 H
1%
13
#1050
0%
03
#1055
b1100100 H
1%
13
#1060
0%
03
#1065
b1100101 H
1%
13
#1070
0%
03
#1075
b1100110 H
1%
13
#1080
0%
03
#1085
b1100111 H
1%
13
#1090
0%
03
#1095
b1101000 H
1%
13
#1100
0%
03
#1105
b1101001 H
1%
13
#1110
0%
03
#1115
b1101010 H
1%
13
#1120
0%
03
#1125
b1101011 H
1%
13
#1130
0%
03
#1135
b1101100 H
1%
13
#1140
0%
03
#1145
b1101101 H
1%
13
#1150
0%
03
#1155
b1101110 H
1%
13
#1160
0%
03
#1165
b1101111 H
1%
13
#1170
0%
03
#1175
b1110000 H
1%
13
#1180
0%
03
#1185
b1110001 H
1%
13
#1190
0%
03
#1195
b1110010 H
1%
13
#1200
0%
03
#1205
b1110011 H
1%
13
#1210
0%
03
#1215
b1110100 H
1%
13
#1220
0%
03
#1225
b1110101 H
1%
13
#1230
0%
03
#1235
b1110110 H
1%
13
#1240
0%
03
#1245
b1110111 H
1%
13
#1250
0%
03
#1255
b1111000 H
1%
13
#1260
0%
03
#1265
b1111001 H
1%
13
#1270
0%
03
#1275
b1111010 H
1%
13
#1280
0%
03
#1285
b1111011 H
1%
13
#1290
0%
03
#1295
b1111100 H
1%
13
#1300
0%
03
#1305
b1111101 H
1%
13
#1310
0%
03
#1315
b1111110 H
1%
13
#1320
0%
03
#1325
b1 F
b100000010100000100100000 D
1,
1/
b1111111 H
12
1%
13
#1330
0%
03
#1335
b1 4
b1 =
b1 G
1I
1"
0,
0/
b1 F
b100000010100000100100000 D
18
b0 H
02
b1 E
b1 )
b1 ;
b100000010100000100100000 C
1%
13
#1340
0%
03
#1345
b1 H
1%
13
#1350
0%
03
#1355
b10 H
1%
13
#1360
0%
03
#1365
b11 H
1%
13
#1370
0%
03
#1375
b100 H
1%
13
#1380
0%
03
#1385
b101 H
1%
13
#1390
0%
03
#1395
b110 H
1%
13
#1400
0%
03
#1405
b111 H
1%
13
#1410
0%
03
#1415
b1000 H
1%
13
#1420
0%
03
#1425
b1001 H
1%
13
#1430
0%
03
#1435
b1010 H
1%
13
#1440
0%
03
#1445
b1011 H
1%
13
#1450
0%
03
#1455
b1100 H
1%
13
#1460
0%
03
#1465
b1101 H
1%
13
#1470
0%
03
#1475
b1110 H
1%
13
#1480
0%
03
#1485
b1111 H
1%
13
#1490
0%
03
#1495
b10000 H
1%
13
#1500
0%
03
#1505
b10001 H
1%
13
#1510
0%
03
#1515
b10010 H
1%
13
#1520
0%
03
#1525
b10011 H
1%
13
#1530
0%
03
#1535
b10100 H
1%
13
#1540
0%
03
#1545
b10101 H
1%
13
#1550
0%
03
#1555
b10110 H
1%
13
#1560
0%
03
#1565
b10111 H
1%
13
#1570
0%
03
#1575
b11000 H
1%
13
#1580
0%
03
#1585
b11001 H
1%
13
#1590
0%
03
#1595
b11010 H
1%
13
#1600
0%
03
#1605
b11011 H
1%
13
#1610
0%
03
#1615
b11100 H
1%
13
#1620
0%
03
#1625
b11101 H
1%
13
#1630
0%
03
#1635
b11110 H
1%
13
#1640
0%
03
#1645
b11111 H
1%
13
#1650
0%
03
#1655
b100000 H
1%
13
#1660
0%
03
#1665
b100001 H
1%
13
#1670
0%
03
#1675
b100010 H
1%
13
#1680
0%
03
#1685
b100011 H
1%
13
#1690
0%
03
#1695
b100100 H
1%
13
#1700
0%
03
#1705
b100101 H
1%
13
#1710
0%
03
#1715
b100110 H
1%
13
#1720
0%
03
#1725
b100111 H
1%
13
#1730
0%
03
#1735
b101000 H
1%
13
#1740
0%
03
#1745
b101001 H
1%
13
#1750
0%
03
#1755
b101010 H
1%
13
#1760
0%
03
#1765
b101011 H
1%
13
#1770
0%
03
#1775
b101100 H
1%
13
#1780
0%
03
#1785
b101101 H
1%
13
#1790
0%
03
#1795
b101110 H
1%
13
#1800
0%
03
#1805
b101111 H
1%
13
#1810
0%
03
#1815
b110000 H
1%
13
#1820
0%
03
#1825
b110001 H
1%
13
#1830
0%
03
#1835
b110010 H
1%
13
#1840
0%
03
#1845
b110011 H
1%
13
#1850
0%
03
#1855
b110100 H
1%
13
#1860
0%
03
#1865
b110101 H
1%
13
#1870
0%
03
#1875
b110110 H
1%
13
#1880
0%
03
#1885
b110111 H
1%
13
#1890
0%
03
#1895
b111000 H
1%
13
#1900
0%
03
#1905
b111001 H
1%
13
#1910
0%
03
#1915
b111010 H
1%
13
#1920
0%
03
#1925
b111011 H
1%
13
#1930
0%
03
#1935
b111100 H
1%
13
#1940
0%
03
#1945
b111101 H
1%
13
#1950
0%
03
#1955
b111110 H
1%
13
#1960
0%
03
#1965
b111111 H
1%
13
#1970
0%
03
#1975
b1000000 H
1%
13
#1980
0%
03
#1985
b1000001 H
1%
13
#1990
0%
03
#1995
b1000010 H
1%
13
#2000
0%
03
#2005
b1000011 H
1%
13
#2010
0%
03
#2015
b1000100 H
1%
13
#2020
0%
03
#2025
b1000101 H
1%
13
#2030
0%
03
#2035
b1000110 H
1%
13
#2040
0%
03
#2045
b1000111 H
1%
13
#2050
0%
03
#2055
b1001000 H
1%
13
#2060
0%
03
#2065
b1001001 H
1%
13
#2070
0%
03
#2075
b1001010 H
1%
13
#2080
0%
03
#2085
b1001011 H
1%
13
#2090
0%
03
#2095
b1001100 H
1%
13
#2100
0%
03
#2105
b1001101 H
1%
13
#2110
0%
03
#2115
b1001110 H
1%
13
#2120
0%
03
#2125
b1001111 H
1%
13
#2130
0%
03
#2135
b1010000 H
1%
13
#2140
0%
03
#2145
b1010001 H
1%
13
#2150
0%
03
#2155
b1010010 H
1%
13
#2160
0%
03
#2165
b1010011 H
1%
13
#2170
0%
03
#2175
b1010100 H
1%
13
#2180
0%
03
#2185
b1010101 H
1%
13
#2190
0%
03
#2195
b1010110 H
1%
13
#2200
0%
03
#2205
b1010111 H
1%
13
#2210
0%
03
#2215
b1011000 H
1%
13
#2220
0%
03
#2225
b1011001 H
1%
13
#2230
0%
03
#2235
b1011010 H
1%
13
#2240
0%
03
#2245
b1011011 H
1%
13
#2250
0%
03
#2255
0I
0"
b1011100 H
1%
13
#2260
0%
03
#2265
b1011101 H
1%
13
#2270
0%
03
#2275
b1011110 H
1%
13
#2280
0%
03
#2285
b1011111 H
1%
13
#2290
0%
03
#2295
b1100000 H
1%
13
#2300
0%
03
#2305
b1100001 H
1%
13
#2310
0%
03
#2315
b1100010 H
1%
13
#2320
0%
03
#2325
b1100011 H
1%
13
#2330
0%
03
#2335
b1100100 H
1%
13
#2340
0%
03
#2345
b1100101 H
1%
13
#2350
0%
03
#2355
b1100110 H
1%
13
#2360
0%
03
#2365
b1100111 H
1%
13
#2370
0%
03
#2375
b1101000 H
1%
13
#2380
0%
03
#2385
b1101001 H
1%
13
#2390
0%
03
#2395
b1101010 H
1%
13
#2400
0%
03
#2405
b1101011 H
1%
13
#2410
0%
03
#2415
b1101100 H
1%
13
#2420
0%
03
#2425
b1101101 H
1%
13
#2430
0%
03
#2435
b1101110 H
1%
13
#2440
0%
03
#2445
b1101111 H
1%
13
#2450
0%
03
#2455
b1110000 H
1%
13
#2460
0%
03
#2465
b1110001 H
1%
13
#2470
0%
03
#2475
b1110010 H
1%
13
#2480
0%
03
#2485
b1110011 H
1%
13
#2490
0%
03
#2495
b1110100 H
1%
13
#2500
0%
03
#2505
b1110101 H
1%
13
#2510
0%
03
#2515
b1110110 H
1%
13
#2520
0%
03
#2525
b1110111 H
1%
13
#2530
0%
03
#2535
b1111000 H
1%
13
#2540
0%
03
#2545
b1111001 H
1%
13
#2550
0%
03
#2555
b1111010 H
1%
13
#2560
0%
03
#2565
b1111011 H
1%
13
#2570
0%
03
#2575
b1111100 H
1%
13
#2580
0%
03
#2585
b1111101 H
1%
13
#2590
0%
03
#2595
b1111110 H
1%
13
#2600
0%
03
#2605
b10 F
b101000001001000001 D
1,
1/
b1111111 H
12
1%
13
#2610
0%
03
#2615
b0 4
b0 =
b0 G
1I
1"
0,
0/
b10 F
b101000001001000001 D
08
b0 H
02
b10 E
b10 )
b10 ;
b101000001001000001 C
1%
13
#2620
0%
03
#2625
b1 H
1%
13
#2630
0%
03
#2635
b10 H
1%
13
#2640
0%
03
#2645
b11 H
1%
13
#2650
0%
03
#2655
b100 H
1%
13
#2660
0%
03
#2665
b101 H
1%
13
#2670
0%
03
#2675
b110 H
1%
13
#2680
0%
03
#2685
b111 H
1%
13
#2690
0%
03
#2695
b1000 H
1%
13
#2700
0%
03
#2705
b1001 H
1%
13
#2710
0%
03
#2715
b1010 H
1%
13
#2720
0%
03
#2725
b1011 H
1%
13
#2730
0%
03
#2735
b1100 H
1%
13
#2740
0%
03
#2745
b1101 H
1%
13
#2750
0%
03
#2755
b1110 H
1%
13
#2760
0%
03
#2765
b1111 H
1%
13
#2770
0%
03
#2775
b10000 H
1%
13
#2780
0%
03
#2785
b10001 H
1%
13
#2790
0%
03
#2795
b10010 H
1%
13
#2800
0%
03
#2805
b10011 H
1%
13
#2810
0%
03
#2815
b10100 H
1%
13
#2820
0%
03
#2825
b10101 H
1%
13
#2830
0%
03
#2835
b10110 H
1%
13
#2840
0%
03
#2845
b10111 H
1%
13
#2850
0%
03
#2855
b11000 H
1%
13
#2860
0%
03
#2865
b11001 H
1%
13
#2870
0%
03
#2875
b11010 H
1%
13
#2880
0%
03
#2885
b11011 H
1%
13
#2890
0%
03
#2895
b11100 H
1%
13
#2900
0%
03
#2905
b11101 H
1%
13
#2910
0%
03
#2915
b11110 H
1%
13
#2920
0%
03
#2925
b11111 H
1%
13
#2930
0%
03
#2935
b100000 H
1%
13
#2940
0%
03
#2945
b100001 H
1%
13
#2950
0%
03
#2955
b100010 H
1%
13
#2960
0%
03
#2965
b100011 H
1%
13
#2970
0%
03
#2975
0I
0"
b100100 H
1%
13
#2980
0%
03
#2985
b100101 H
1%
13
#2990
0%
03
#2995
b100110 H
1%
13
#3000
0%
03
#3005
b100111 H
1%
13
#3010
0%
03
#3015
b101000 H
1%
13
#3020
0%
03
#3025
b101001 H
1%
13
#3030
0%
03
#3035
b101010 H
1%
13
#3040
0%
03
#3045
b101011 H
1%
13
#3050
0%
03
#3055
b101100 H
1%
13
#3060
0%
03
#3065
b101101 H
1%
13
#3070
0%
03
#3075
b101110 H
1%
13
#3080
0%
03
#3085
b101111 H
1%
13
#3090
0%
03
#3095
b110000 H
1%
13
#3100
0%
03
#3105
b110001 H
1%
13
#3110
0%
03
#3115
b110010 H
1%
13
#3120
0%
03
#3125
b110011 H
1%
13
#3130
0%
03
#3135
b110100 H
1%
13
#3140
0%
03
#3145
b110101 H
1%
13
#3150
0%
03
#3155
b110110 H
1%
13
#3160
0%
03
#3165
b110111 H
1%
13
#3170
0%
03
#3175
b111000 H
1%
13
#3180
0%
03
#3185
b111001 H
1%
13
#3190
0%
03
#3195
b111010 H
1%
13
#3200
0%
03
